StardewValley/__init__.py
StardewValley/contentpatcher.py
StardewValley/create.py
StardewValley/frameworks.py
StardewValley/helper.py
StardewValley/itemextensions.py
StardewValley/jsonreader.py
StardewValley/manifest.py
StardewValley/slingshot.py
StardewValley/verification.py
StardewValley/Characters/__init__.py
StardewValley/Characters/dialogues.py
StardewValley/Characters/schedules.py
StardewValley/Data/Achievements.py
StardewValley/Data/AdditionalFarms.py
StardewValley/Data/AdditionalWallpaperFlooring.py
StardewValley/Data/AnimationDescriptions.py
StardewValley/Data/AquariumFish.py
StardewValley/Data/AudioChanges.py
StardewValley/Data/BigCraftables.py
StardewValley/Data/Boots.py
StardewValley/Data/Buffs.py
StardewValley/Data/Buildings.py
StardewValley/Data/Bundles.py
StardewValley/Data/ChairTiles.py
StardewValley/Data/Characters.py
StardewValley/Data/ConcessionTastes.py
StardewValley/Data/Concessions.py
StardewValley/Data/CookingRecipes.py
StardewValley/Data/CraftingRecipes.py
StardewValley/Data/Crops.py
StardewValley/Data/EngagementDialogue.py
StardewValley/Data/Events.py
StardewValley/Data/ExtraDialogue.py
StardewValley/Data/FarmAnimals.py
StardewValley/Data/Fences.py
StardewValley/Data/Fish.py
StardewValley/Data/FishPonds.py
StardewValley/Data/FloorsAndPaths.py
StardewValley/Data/FruitTrees.py
StardewValley/Data/Furniture.py
StardewValley/Data/GiantCrops.py
StardewValley/Data/Hair.py
StardewValley/Data/Hats.py
StardewValley/Data/HomeRenovations.py
StardewValley/Data/IncomingPhoneCalls.py
StardewValley/Data/JukeboxTracks.py
StardewValley/Data/LocationContexts.py
StardewValley/Data/Locations.py
StardewValley/Data/LostItemsShop.py
StardewValley/Data/Machines.py
StardewValley/Data/MakeoverOutfits.py
StardewValley/Data/Mannequins.py
StardewValley/Data/Minecarts.py
StardewValley/Data/MonsterSlayerQuests.py
StardewValley/Data/Monsters.py
StardewValley/Data/Movies.py
StardewValley/Data/MoviesReactions.py
StardewValley/Data/MuseumRewards.py
stardewmodpy-0.3.11.post1.dist-info/licenses/LICENSE
stardewmodpy-0.3.11.post1.dist-info/METADATA
stardewmodpy-0.3.11.post1.dist-info/WHEEL
stardewmodpy-0.3.11.post1.dist-info/entry_points.txt
stardewmodpy-0.3.11.post1.dist-info/top_level.txt
stardewmodpy-0.3.11.post1.dist-info/RECORD
