Metadata-Version: 2.4
Name: stardewModPY
Version: 0.3.11.post1
Summary: Uma biblioteca para gerar mods com packs de conteúdo em json para Stardew Valley
Home-page: 
Author: alichan
Author-email: suportestardewmodspy@gmail.com
Project-URL: Documentação, http://stardewmodpy.kya.app.br/
Project-URL: Suporte, https://discord.gg/Pxj3EDafsv
Classifier: Programming Language :: Python :: 3
Classifier: Operating System :: OS Independent
Requires-Python: >=3.12
License-File: LICENSE
Requires-Dist: prettytable
Dynamic: author
Dynamic: author-email
Dynamic: classifier
Dynamic: description
Dynamic: description-content-type
Dynamic: license-file
Dynamic: project-url
Dynamic: requires-dist
Dynamic: requires-python
Dynamic: summary
